logfit/__init__.py
logfit/client.py
logfit/config.py
logfit/daemon.py
logfit/main.py
logfit/tail.py
logfit-1.1.1.dist-info/METADATA
logfit-1.1.1.dist-info/WHEEL
logfit-1.1.1.dist-info/entry_points.txt
logfit-1.1.1.dist-info/top_level.txt
logfit-1.1.1.dist-info/RECORD
