Metadata-Version: 2.1
Name: logfit
Version: 1.1.1
Summary: Watch and upload log files to log.fit
Home-page: https://github.com/albertyw/logfit-daemon
Author: Albert Wang
Author-email: daemon@log.fit
License: MIT
Keywords: logfit log.fit logging monitoring alerting
Platform: UNKNOWN
Classifier: Development Status :: 4 - Beta
Classifier: Intended Audience :: Developers
Classifier: Natural Language :: English
Classifier: Topic :: Internet :: Log Analysis
Classifier: Topic :: System :: Logging
Classifier: Topic :: System :: Monitoring
Classifier: License :: OSI Approved :: MIT License
Classifier: Programming Language :: Python :: 3
Classifier: Programming Language :: Python :: 3.3
Classifier: Programming Language :: Python :: 3.4
Classifier: Programming Language :: Python :: 3.5
Classifier: Programming Language :: Python :: 3.6
Requires-Dist: requests
Requires-Dist: rollbar
Requires-Dist: python-magic
Requires-Dist: pyyaml
Provides-Extra: dev
Requires-Dist: PyInstaller (==3.2.1) ; extra == 'dev'
Provides-Extra: test
